pkg/__init__.py
pkg/tr.py
hmktr-0.7.dist-info/LICENSE.txt
hmktr-0.7.dist-info/METADATA
hmktr-0.7.dist-info/WHEEL
hmktr-0.7.dist-info/top_level.txt
hmktr-0.7.dist-info/RECORD
